terry_toolbox/__init__.py
terry_toolbox/read.py
terry_toolbox/tensor_tool.py
terry_toolbox/video.py
terry_toolbox/write.py
terry_toolbox/mujoco/__init__.py
terry_toolbox/mujoco/image.py
terry_toolbox/resources/__init__.py
toolbox/__init__.py
toolbox/read.py
toolbox/tensor_tool.py
toolbox/video.py
toolbox/write.py
toolbox/mujoco/__init__.py
toolbox/mujoco/image.py
toolbox/resources/__init__.py
terry_toolbox-1.0.0.dist-info/METADATA
terry_toolbox-1.0.0.dist-info/WHEEL
terry_toolbox-1.0.0.dist-info/top_level.txt
terry_toolbox-1.0.0.dist-info/RECORD
